setuptools_scrutinize/__init__.py
setuptools_scrutinize/cmd.py
setuptools_scrutinize/pylint.py
setuptools_scrutinize/setuptools_command.py
setuptools_scrutinize-0.0.1.dist-info/LICENSE
setuptools_scrutinize-0.0.1.dist-info/METADATA
setuptools_scrutinize-0.0.1.dist-info/WHEEL
setuptools_scrutinize-0.0.1.dist-info/entry_points.txt
setuptools_scrutinize-0.0.1.dist-info/top_level.txt
setuptools_scrutinize-0.0.1.dist-info/RECORD
