Metadata-Version: 2.1
Name: setuptools-scrutinize
Version: 0.0.1
Summary: A Setuptools plugin
Home-page: https://github.com/mikkoi/setuptools-scrutinize
Author: Mikko Koivunalho
Author-email: mikko.koivunalho@iki.fi
License: BSD
Keywords: scrutinize,setuptools,command
Platform: UNKNOWN
Classifier: Framework :: Setuptools Plugin
Classifier: Development Status :: 4 - Beta
Classifier: Intended Audience :: Developers
Classifier: Operating System :: OS Independent
Classifier: Programming Language :: Python :: 3.6
Classifier: License :: OSI Approved :: BSD License
Requires-Python: >=3.6
